{
  "project_info": {
    "project_number": "127042385908",
    "project_id": "betaeatme",
    "storage_bucket": "betaeatme.firebasestorage.app"
  },
  "client": [
    {
      "client_info": {
        "mobilesdk_app_id": "1:127042385908:android:3489247602da28119daba1",
        "android_client_info": {
          "package_name": "com.eatme.app"
        }
      },
      "oauth_client": [
        {
          "client_id": "127042385908-277q5qrovkfh11jcnbsn6pk47jbludql.apps.googleusercontent.com",
          "client_type": 1,
          "android_info": {
            "package_name": "com.eatme.app",
            "certificate_hash": "88350b79a200920bedf6e31a727fa5bea5b0f7f5"
          }
        },
        {
          "client_id": "127042385908-6d5dh5qlbfvgs2lcmj9ker73kg4cqofh.apps.googleusercontent.com",
          "client_type": 1,
          "android_info": {
            "package_name": "com.eatme.app",
            "certificate_hash": "5e8f16062ea3cd2c4a0d547876baa6f38cabf625"
          }
        },
        {
          "client_id": "127042385908-80e5kctool2dmm8060qftoobfhnhrflc.apps.googleusercontent.com",
          "client_type": 3
        }
      ],
      "api_key": [
        {
          "current_key": "AIzaSyD6Y6FH5UhvfpweuLDXWBYkuApUw06h7qw"
        }
      ],
      "services": {
        "appinvite_service": {
          "other_platform_oauth_client": [
            {
              "client_id": "127042385908-80e5kctool2dmm8060qftoobfhnhrflc.apps.googleusercontent.com",
              "client_type": 3
            }
          ]
        }
      }
    }
  ],
  "configuration_version": "1"
}